nile/__init__.py
nile/accounts.py
nile/cli.py
nile/common.py
nile/deployments.py
nile/nre.py
nile/signer.py
nile/artifacts/Account.json
nile/artifacts/abis/Account.json
nile/artifacts/abis/ERC20.json
nile/base_project/.env
nile/base_project/.gitignore
nile/base_project/contracts/contract.cairo
nile/base_project/tests/test_contract.py
nile/core/call_or_invoke.py
nile/core/clean.py
nile/core/compile.py
nile/core/declare.py
nile/core/deploy.py
nile/core/init.py
nile/core/node.py
nile/core/plugins.py
nile/core/run.py
nile/core/test.py
nile/core/version.py
nile/core/types/account.py
nile/core/types/transactions.py
nile/core/types/tx_wrappers.py
nile/core/types/udc_helpers.py
nile/core/types/utils.py
nile/starknet_cli/__init__.py
nile/starknet_cli/deploy_account.py
nile/utils/__init__.py
nile/utils/common.py
nile/utils/get_accounts.py
nile/utils/get_balance.py
nile/utils/get_nonce.py
nile/utils/status.py
nile/utils/test.py
cairo_nile-0.14.0.dist-info/LICENSE
cairo_nile-0.14.0.dist-info/METADATA
cairo_nile-0.14.0.dist-info/WHEEL
cairo_nile-0.14.0.dist-info/entry_points.txt
cairo_nile-0.14.0.dist-info/top_level.txt
cairo_nile-0.14.0.dist-info/RECORD
