Metadata-Version: 2.1
Name: cairo-nile
Version: 0.14.0
Summary: StarkNet/Cairo development toolbelt
Home-page: https://github.com/martriay/nile
Author: Martin Triay
Author-email: martriay@gmail.com
License: MIT
Platform: any
Classifier: Programming Language :: Python :: 3.9
Classifier: Operating System :: OS Independent
Requires-Python: <3.10,>=3.8
License-File: LICENSE
Requires-Dist: anyio (>=3.6.1)
Requires-Dist: asyncclick (>=8.1.3.4)
Requires-Dist: click (<9.0,>=8.0)
Requires-Dist: importlib-metadata (>=4.0)
Requires-Dist: python-dotenv (>=0.19.2)
Requires-Dist: cairo-lang (>=0.11.0.2)
Requires-Dist: starknet-devnet (>=0.5.0)
Requires-Dist: pytest (>=7.1.3)
Requires-Dist: pytest-asyncio (>=0.19.0)
Requires-Dist: requests (>=2.28.1)
Provides-Extra: testing
Requires-Dist: setuptools ; extra == 'testing'
Requires-Dist: tox ; extra == 'testing'
Requires-Dist: twine ; extra == 'testing'
Requires-Dist: pytest ; extra == 'testing'
Requires-Dist: pytest-cov ; extra == 'testing'
